pyxie/__init__.py
pyxie/cache.py
pyxie/collection.py
pyxie/constants.py
pyxie/errors.py
pyxie/fasthtml.py
pyxie/layouts.py
pyxie/parser.py
pyxie/py.typed
pyxie/pyxie.py
pyxie/query.py
pyxie/renderer.py
pyxie/slots.py
pyxie/types.py
pyxie/utilities.py
pyx2-0.1.3.dist-info/METADATA
pyx2-0.1.3.dist-info/WHEEL
pyx2-0.1.3.dist-info/licenses/LICENSE
pyx2-0.1.3.dist-info/licenses/LICENSE_HEADER.txt
pyx2-0.1.3.dist-info/RECORD
