Metadata-Version: 2.4
Name: pyx2
Version: 0.1.3
Summary: Create flexible websites with markdown content and FastHTML layouts - no design constraints
Project-URL: Source, https://github.com/banditburai/pyxie
Project-URL: Bug Tracker, https://github.com/banditburai/pyxie/issues
Author-email: firefly <promptsiren@gmail.com>
License: Apache-2.0
License-File: LICENSE
License-File: LICENSE_HEADER.txt
Keywords: blogs,fasthtml,layouts,markdown,static-site,web
Classifier: Development Status :: 4 - Beta
Classifier: Intended Audience :: Developers
Classifier: License :: OSI Approved :: Apache Software License
Classifier: Operating System :: OS Independent
Classifier: Programming Language :: Python :: 3
Classifier: Programming Language :: Python :: 3.11
Classifier: Topic :: Internet :: WWW/HTTP
Classifier: Topic :: Software Development :: Libraries :: Python Modules
Requires-Python: >=3.11
Requires-Dist: lxml>=5.1.0
Requires-Dist: mistletoe>=1.4.0
Requires-Dist: pydantic>=2.10.6
Requires-Dist: python-fasthtml>=0.12.4
